example/__init__.py
example/anime.py
osusume/__init__.py
osusume/base.py
osusume/core.py
osusume/embed.py
osusume/extract.py
osusume/generate.py
osusume/version.py
osusume/util/__init__.py
osusume/util/text.py
tests/__init__.py
osusume-1.0.1.dist-info/METADATA
osusume-1.0.1.dist-info/WHEEL
osusume-1.0.1.dist-info/licenses/LICENSE
osusume-1.0.1.dist-info/RECORD
