Metadata-Version: 2.1
Name: osusume
Version: 1.0.1
Summary: Text-based Recommendation Engine using Cohere NLP
Project-URL: homepage, https://github.com/abhishtagatya/osusume
Project-URL: documentation, https://github.com/abhishtagatya/osusume
Project-URL: changelog, https://github.com/abhishtagatya/osusume/blob/master/CHANGELOG.md
Author-email: Abhishta Gatya <abhishtagatya@yahoo.com>
License:                                  Apache License
License-File: LICENSE
Keywords: cohere,data science,machine learning,recommendation engine
Classifier: Development Status :: 3 - Alpha
Classifier: Intended Audience :: Customer Service
Classifier: Intended Audience :: Developers
Classifier: Intended Audience :: Information Technology
Classifier: Intended Audience :: Science/Research
Classifier: License :: OSI Approved :: Apache Software License
Classifier: Natural Language :: English
Classifier: Operating System :: OS Independent
Classifier: Programming Language :: Python :: 3.6
Classifier: Programming Language :: Python :: 3.7
Classifier: Programming Language :: Python :: 3.8
Classifier: Programming Language :: Python :: 3.9
Classifier: Programming Language :: Python :: 3.10
Classifier: Programming Language :: Python :: 3.11
Classifier: Topic :: Scientific/Engineering :: Artificial Intelligence
Classifier: Topic :: Software Development :: Libraries
Classifier: Topic :: Software Development :: Libraries :: Python Modules
Requires-Python: >=3.8
Requires-Dist: cohere>=2.9.1
Requires-Dist: nltk>=3.7
Requires-Dist: numpy>=1.23.5
Requires-Dist: pandas>=1.5.2
Requires-Dist: scikit-learn>=1.1.3
